flow_controller/__init__.py
flow_controller/keyboard.py
flow_controller/main.py
flow_controller-1.0.5.dist-info/LICENSE
flow_controller-1.0.5.dist-info/METADATA
flow_controller-1.0.5.dist-info/WHEEL
flow_controller-1.0.5.dist-info/top_level.txt
flow_controller-1.0.5.dist-info/RECORD
