Metadata-Version: 2.1
Name: flow-controller
Version: 1.0.5
Summary: package for managing pipelines with simple commands
Home-page: UNKNOWN
Author: Ignace Konig
License: MIT
Platform: UNKNOWN
License-File: LICENSE
Requires-Dist: keyboard
